librecpe/__init__.py
librecpe/documento.py
librecpe/common/__init__.py
librecpe/common/documento.py
librecpe/common/empresa.py
librecpe/common/error.py
librecpe/common/servidor.py
librecpe/cpe/__init__.py
librecpe/cpe/cliente.py
librecpe/cpe/librecpe.py
librecpe/cpe/ubl20.py
librecpe/cpe/ubl21.py
librecpe/nubefact/__init__.py
librecpe/nubefact/nubefact.py
librecpe/tci/__init__.py
librecpe/tci/cliente.py
librecpe/tci/tci.py
librecpe-2.0.1.dist-info/METADATA
librecpe-2.0.1.dist-info/WHEEL
librecpe-2.0.1.dist-info/entry_points.txt
librecpe-2.0.1.dist-info/top_level.txt
librecpe-2.0.1.dist-info/RECORD
