Metadata-Version: 2.4
Name: librecpe
Version: 2.0.1
Summary: Libre CPE
Home-page: https://github.com/GrupoYACCK/librecpe/
Author: Alex Cuellar
Author-email: acuellar@grupoyacck.com
Maintainer: Alex Cuellar
Maintainer-email: acuellar@grupoyacck.com
License: GPLv3
Keywords: librecpe
Classifier: Programming Language :: Python :: 3
Classifier: Programming Language :: Python :: 3.5
Classifier: Programming Language :: Python :: 3.6
Classifier: Programming Language :: Python :: 3.7
Classifier: Programming Language :: Python :: 3.8
Classifier: Programming Language :: Python :: 3.9
Classifier: Programming Language :: Python :: 3.10
Classifier: Programming Language :: Python :: 3.11
Classifier: Programming Language :: Python :: 3.12
Requires-Dist: lxml
Requires-Dist: xmlsec
Requires-Dist: pysimplesoap
Requires-Dist: pytz
Requires-Dist: zeep
Dynamic: author
Dynamic: author-email
Dynamic: classifier
Dynamic: home-page
Dynamic: keywords
Dynamic: license
Dynamic: maintainer
Dynamic: maintainer-email
Dynamic: requires-dist
Dynamic: summary
